LICENSE
README.md
setup.cfg
setup.py
SeqUtils.egg-info/PKG-INFO
SeqUtils.egg-info/SOURCES.txt
SeqUtils.egg-info/dependency_links.txt
SeqUtils.egg-info/requires.txt
SeqUtils.egg-info/top_level.txt
sequtils/__init__.py
sequtils/auth.py
sequtils/email_alerts.py
sequtils/test_email_alerts.py