Metadata-Version: 2.1
Name: SeqUtils
Version: 1.0.7
Summary: SeqUtils - general utilities to aid in system administration and analysis tasks
Home-page: https://github.com/sequencecentral/SeqUtils.git
Author: Steve Ayers, Ph.D.
Author-email: steve@sequenccecentral.com
License: MIT
Platform: UNKNOWN
